imagefourier/__init__.py
imagefourier/imagefourier.py
imagefourier-0.1.3.dist-info/LICENSE
imagefourier-0.1.3.dist-info/METADATA
imagefourier-0.1.3.dist-info/WHEEL
imagefourier-0.1.3.dist-info/top_level.txt
imagefourier-0.1.3.dist-info/RECORD
